resolwe_bio/__init__.py
resolwe_bio/apps.py
resolwe_bio/extensions.py
resolwe_bio/filters.py
resolwe_bio/models.py
resolwe_bio/descriptors/dicty_time_series.yml
resolwe_bio/descriptors/diffexp.yml
resolwe_bio/descriptors/geneset.yml
resolwe_bio/descriptors/reads.yml
resolwe_bio/expression_filters/__init__.py
resolwe_bio/expression_filters/relation.py
resolwe_bio/expression_filters/sample.py
resolwe_bio/fixtures/relationtypes.yaml
resolwe_bio/kb/__init__.py
resolwe_bio/kb/admin.py
resolwe_bio/kb/apps.py
resolwe_bio/kb/backends.py
resolwe_bio/kb/filters.py
resolwe_bio/kb/listener_plugin.py
resolwe_bio/kb/models.py
resolwe_bio/kb/pagination.py
resolwe_bio/kb/serializers.py
resolwe_bio/kb/views.py
resolwe_bio/kb/management/__init__.py
resolwe_bio/kb/management/commands/__init__.py
resolwe_bio/kb/management/commands/insert_features.py
resolwe_bio/kb/management/commands/insert_mappings.py
resolwe_bio/kb/management/commands/utils.py
resolwe_bio/kb/migrations/0001_initial.py
resolwe_bio/kb/migrations/0001_squashed_0012_update_feature_search.py
resolwe_bio/kb/migrations/0002_alter_field_max_length.py
resolwe_bio/kb/migrations/0003_add_map_index.py
resolwe_bio/kb/migrations/0004_add_unique_together.py
resolwe_bio/kb/migrations/0005_species.py
resolwe_bio/kb/migrations/0006_feature_fullname_300.py
resolwe_bio/kb/migrations/0007_feature_fullname_350.py
resolwe_bio/kb/migrations/0008_callable_defaults.py
resolwe_bio/kb/migrations/0009_full_text_search.py
resolwe_bio/kb/migrations/0010_update_indexes_constraints.py
resolwe_bio/kb/migrations/0011_feature_type_index.py
resolwe_bio/kb/migrations/0012_update_feature_search.py
resolwe_bio/kb/migrations/0013_update_feature_search.py
resolwe_bio/kb/migrations/0014_update_feature_search.py
resolwe_bio/kb/migrations/__init__.py
resolwe_bio/kb/migrations/reverse_triggers_feature.sql
resolwe_bio/kb/migrations/triggers_feature.sql
resolwe_bio/kb/migrations/triggers_feature_2.sql
resolwe_bio/kb/tests/__init__.py
resolwe_bio-64.1.0.dist-info/LICENSE
resolwe_bio-64.1.0.dist-info/METADATA
resolwe_bio-64.1.0.dist-info/WHEEL
resolwe_bio-64.1.0.dist-info/top_level.txt
resolwe_bio-64.1.0.dist-info/RECORD
