Metadata-Version: 2.1
Name: resolwe_bio
Version: 64.1.0
Summary: Bioinformatics pipelines for the Resolwe platform
Author-email: "Genialis, Inc" <dev-team@genialis.com>
License: Apache License (2.0)
Project-URL: Homepage, https://github.com/genialis/resolwe-bio
Project-URL: Documentation, https://resolwe-bio.readthedocs.io/en/latest/
Project-URL: Repository, https://github.com/genialis/resolwe-bio
Keywords: bioinformatics,resolwe,bio,pipelines,dataflow,django
Classifier: Development Status :: 5 - Production/Stable
Classifier: Environment :: Web Environment
Classifier: Framework :: Django
Classifier: Intended Audience :: Developers
Classifier: Topic :: Scientific/Engineering :: Bio-Informatics
Classifier: Topic :: Software Development :: Libraries :: Python Modules
Classifier: License :: OSI Approved :: Apache Software License
Classifier: Operating System :: OS Independent
Classifier: Programming Language :: Python
Classifier: Programming Language :: Python :: 3
Classifier: Programming Language :: Python :: 3.11
Classifier: Programming Language :: Python :: 3.12
Classifier: Programming Language :: Python :: 3.13
Requires-Python: <3.14,>=3.10
License-File: LICENSE
Requires-Dist: Django~=5.2.0
Requires-Dist: djangorestframework~=3.16.0
Requires-Dist: django-filter~=25.1
Requires-Dist: resolwe==45.*
Requires-Dist: wrapt~=1.17.2
Provides-Extra: test
Requires-Dist: build==1.2.2; extra == "test"
Requires-Dist: black==25.1.0; extra == "test"
Requires-Dist: check-manifest; extra == "test"
Requires-Dist: colorama; extra == "test"
Requires-Dist: django-stubs>=5.2.0; extra == "test"
Requires-Dist: django-filter-stubs>=0.1.3; extra == "test"
Requires-Dist: daphne; extra == "test"
Requires-Dist: flake8>=7.2.0; extra == "test"
Requires-Dist: isort>=6.0.1; extra == "test"
Requires-Dist: mypy>=1.15.0; extra == "test"
Requires-Dist: pydocstyle~=6.3.0; extra == "test"
Requires-Dist: setuptools_scm; extra == "test"
Requires-Dist: six==1.17; extra == "test"
Requires-Dist: tblib>=3.1.0; extra == "test"
Requires-Dist: twine==6.1.0; extra == "test"
Provides-Extra: docs
Requires-Dist: daphne; extra == "docs"
Requires-Dist: Sphinx~=8.2.3; extra == "docs"
Requires-Dist: sphinx-rtd-theme==3.0.2; extra == "docs"
Requires-Dist: pyasn1>=0.6.1; extra == "docs"
Provides-Extra: package
Requires-Dist: twine; extra == "package"
Requires-Dist: wheel; extra == "package"
Requires-Dist: check-manifest; extra == "package"
Requires-Dist: setuptools_scm; extra == "package"
